ame/__init__.py
ame/core/__init__.py
ame/core/agent_with_tools.py
ame/core/chat_context.py
ame/core/tools.py
ame/llms/__init__.py
ame/llms/llm.py
ame/llms/anthropic/llm.py
ame/llms/anthropic/models.py
ame/llms/anthropic/utils.py
ame/llms/gemini/llm.py
ame/llms/gemini/models.py
ame/llms/gemini/utils.py
agents_made_easy-0.1.4.dist-info/METADATA
agents_made_easy-0.1.4.dist-info/WHEEL
agents_made_easy-0.1.4.dist-info/RECORD
